flood_geoai/__init__.py
flood_geoai/cli.py
flood_geoai/core.py
flood_geoai/utils.py
flood_geoai/data/__init__.py
flood_geoai_tool-0.1.0.dist-info/licenses/LICENSE
flood_geoai_tool-0.1.0.dist-info/METADATA
flood_geoai_tool-0.1.0.dist-info/WHEEL
flood_geoai_tool-0.1.0.dist-info/entry_points.txt
flood_geoai_tool-0.1.0.dist-info/top_level.txt
flood_geoai_tool-0.1.0.dist-info/RECORD
