Metadata-Version: 2.4
Name: flood-geoai-tool
Version: 0.1.0
Summary: A GeoAI tool for flood risk assessment using satellite imagery
Author-email: Your Name <your.email@example.com>
License: MIT
Requires-Python: >=3.8
License-File: LICENSE
Requires-Dist: rasterio>=1.2.0
Requires-Dist: geopandas>=0.10.0
Requires-Dist: torch>=1.9.0
Requires-Dist: scikit-image>=0.18.0
Requires-Dist: numpy>=1.21.0
Requires-Dist: shapely>=1.8.0
Requires-Dist: fiona>=1.8.0
Requires-Dist: pillow>=8.0.0
Dynamic: license-file
